src/__init__.py
src/cli.py
src/config.py
src/main.py
google_search_scraper-0.1.0.dist-info/AUTHORS.rst
google_search_scraper-0.1.0.dist-info/LICENSE
google_search_scraper-0.1.0.dist-info/METADATA
google_search_scraper-0.1.0.dist-info/WHEEL
google_search_scraper-0.1.0.dist-info/entry_points.txt
google_search_scraper-0.1.0.dist-info/top_level.txt
google_search_scraper-0.1.0.dist-info/RECORD
