Metadata-Version: 2.1
Name: google-search-scraper
Version: 0.1.0
Summary: a python package to scrape google search results
Home-page: https://github.com/nidhaloff/google_search_scraper
Author: Nidhal Baccouri
Author-email: nidhalbacc@gmail.com
License: Apache Software License 2.0
Keywords: google_search_scraper
Platform: UNKNOWN
Classifier: Development Status :: 2 - Pre-Alpha
Classifier: Intended Audience :: Developers
Classifier: License :: OSI Approved :: Apache Software License
Classifier: Natural Language :: English
Classifier: Programming Language :: Python :: 3
Classifier: Programming Language :: Python :: 3.5
Classifier: Programming Language :: Python :: 3.6
Classifier: Programming Language :: Python :: 3.7
Classifier: Programming Language :: Python :: 3.8
Requires-Python: >=3.5
